{"cameraMode":{"drawMode":0,"name":"Shaded","section":"Shading Mode"},"sceneLighting":false,"audioPlay":false,"sceneViewState":{"m_AlwaysRefresh":false,"showFog":true,"showSkybox":false,"showFlares":true,"showImageEffects":true,"showParticleSystems":true,"showVisualEffectGraphs":true,"m_FxEnabled":true},"in2DMode":false,"pivot":{"x":-2.30519700050354,"y":3.210355758666992,"z":-9.067155838012696},"rotation":{"x":0.2923848032951355,"y":0.6494582891464233,"z":-0.2989535629749298,"w":0.6351487636566162},"size":0.9949875473976135,"orthographic":false}